{"stat.useItem.274":32,"stat.craftItem.263":4,"stat.useItem.275":54,"stat.walkOneCm":278584,"stat.useItem.61":1,"achievement.buildHoe":1,"stat.craftItem.61":1,"stat.leaveGame":2,"stat.mineBlock.175":1,"stat.killEntity.fiskheroes.Creetle":6,"stat.mineBlock.58":1,"stat.mineBlock.16":22,"stat.mineBlock.15":6,"stat.mineBlock.18":8,"stat.mineBlock.17":34,"stat.jump":666,"stat.swimOneCm":6278,"stat.fallOneCm":14066,"stat.craftItem.291":1,"achievement.buildWorkBench":3,"stat.entityKilledBy.Skeleton":2,"stat.entityKilledBy.fiskheroes.Creetle":4,"achievement.mineWood":38,"stat.useItem.39":1,"achievement.exploreAllBiomes":{"value":0,"progress":["ForestHills","Birch Forest","Forest","River","Taiga","Extreme Hills"]},"stat.useItem.291":5,"achievement.fiskheroes.killCreetle":6,"stat.killEntity.Skeleton":4,"stat.breakItem.270":1,"stat.craftItem.320":2,"stat.craftItem.364":4,"achievement.openInventory":32,"stat.craftItem.5":136,"stat.craftItem.280":16,"stat.damageTaken":3285,"stat.killEntity.Spider":1,"stat.mineBlock.3":11,"stat.mineBlock.1":94,"stat.mineBlock.61":1,"stat.mobKills":25,"achievement.buildFurnace":2,"stat.flyOneCm":92634,"stat.craftItem.58":2,"stat.craftItem.274":2,"stat.useItem.6":1,"stat.mineBlock.38":1,"stat.deaths":10,"stat.craftItem.275":1,"stat.drop":83,"stat.mineBlock.39":4,"achievement.buildPickaxe":8,"stat.useItem.268":44,"stat.playOneMinute":50448,"stat.killEntity.Sheep":6,"stat.useItem.4":1,"stat.craftItem.270":2,"stat.craftItem.271":1,"stat.useItem.3":6,"stat.damageDealt":3970,"achievement.buildBetterPickaxe":4,"stat.killEntity.Cow":3,"stat.killEntity.Pig":3,"stat.useItem.270":96,"stat.useItem.58":2,"stat.mineBlock.31":164,"stat.diveOneCm":3104,"stat.useItem.15":1,"stat.useItem.271":1}